sqlcompose/__init__.py
sqlcompose/__main__.py
sqlcompose/py.typed
sqlcompose/core/app.py
sqlcompose/core/circular_dependency_error.py
sqlcompose/core/compat.py
sqlcompose/core/functions.py
sqlcompose/core/include.py
sqlcompose-0.0.3.dist-info/licenses/LICENSE
sqlcompose-0.0.3.dist-info/METADATA
sqlcompose-0.0.3.dist-info/WHEEL
sqlcompose-0.0.3.dist-info/entry_points.txt
sqlcompose-0.0.3.dist-info/top_level.txt
sqlcompose-0.0.3.dist-info/RECORD
