Metadata-Version: 2.4
Name: sqlcompose
Version: 0.0.3
Summary: Composition of linked SQL files
Author-email: Anders Madsen <anders.madsen@alphavue.com>
License: MIT
Project-URL: repository, https://github.com/apmadsen/sqlcompose
Keywords: sql,composition,windows,linux
Classifier: Development Status :: 5 - Production/Stable
Classifier: Development Status :: 6 - Mature
Classifier: Operating System :: Microsoft :: Windows
Classifier: Operating System :: POSIX :: Linux
Classifier: Intended Audience :: Developers
Classifier: Natural Language :: English
Classifier: Programming Language :: Python :: 3 :: Only
Classifier: Programming Language :: Python :: 3
Classifier: Programming Language :: Python :: 3.10
Classifier: Programming Language :: Python :: 3.11
Classifier: Programming Language :: Python :: 3.12
Classifier: Programming Language :: Python :: 3.13
Classifier: Programming Language :: Python
Classifier: Topic :: Software Development :: Libraries :: Python Modules
Classifier: Topic :: Software Development :: Libraries
Classifier: Typing :: Typed
Requires-Python: >=3.10
License-File: LICENSE
Provides-Extra: test
Requires-Dist: pytest>=8.3.0; extra == "test"
Requires-Dist: pytest-cov>=6.1.0; extra == "test"
Dynamic: license-file
